{
  "$schema": "https://turbo.build/schema.json",
  "extends": ["//"],
  "pipeline": {
    "build": {
      "cache": true,
      "inputs": [
        "../../platform/config-typescript/tsconfig.json",
        "src/**",
        "test/**",
        "package.json",
        "tsconfig.build.json"
      ],
      "outputs": ["*.tsbuildinfo"]
    },
    "lint": {
      "cache": true,
      "inputs": [
        "../../platform/config-typescript/tsconfig.json",
        "../../platform/config-eslint/eslint-ecma.cjs",
        "src/**",
        "test/**",
        ".eslintrc.js",
        "package.json",
        "tsconfig.build.json",
        "tsconfig.project.json"
      ],
      "outputs": []
    },
    "lint:fix": {
      "cache": true,
      "inputs": [
        "../../platform/config-typescript/tsconfig.json",
        "../../platform/config-eslint/eslint-ecma.cjs",
        "src/**",
        "test/**",
        ".eslintrc.js",
        "package.json",
        "tsconfig.build.json",
        "tsconfig.project.json"
      ],
      "outputs": ["src/**", "test/**"]
    }
  }
}
